algebra/__init__.py
algebra/components-test.py
algebra/components.py
algebra/test/__init__.py
algebra/test/comp.py
algebra_py-1.4.1.dist-info/licenses/LICENSE
algebra_py-1.4.1.dist-info/METADATA
algebra_py-1.4.1.dist-info/WHEEL
algebra_py-1.4.1.dist-info/top_level.txt
algebra_py-1.4.1.dist-info/RECORD
