Metadata-Version: 2.4
Name: algebra.py
Version: 1.4.1
Summary: A simple python package for algebraic calculations
Home-page: https://github.com/chouettevan/algebra
Author-email: pybots743@gmail.com
Classifier: Programming Language :: Python :: 3
Classifier: License :: OSI Approved :: MIT License
Classifier: Operating System :: OS Independent
Requires-Python: >=3.8
License-File: LICENSE
Dynamic: license-file
